ecc/lfsr_generic.vhd
-------------------------------------------------------------------------------
-- Title      : LFSR
-- Project    : 
-------------------------------------------------------------------------------
-- File	      : lfsr.vhd
-- Author     : Efe  <efe@efeASUS>
-- Company    : 
-- Created    : 2022-10-09
-- Last update: 2022-10-10
-- Platform   : 
-- Standard   : VHDL'93/02
-------------------------------------------------------------------------------
-- Description: 
-------------------------------------------------------------------------------
-- Copyright (c) 2022 
-------------------------------------------------------------------------------
-- Revisions  :
-- Date	       Version	Author	Description
-- 2022-10-09  1.0	efe	Created
-------------------------------------------------------------------------------


library ieee;
use ieee.std_logic_1164.all;
use ieee.numeric_std.all;


entity lfsr_generic is

    generic (
	WIDTH : integer := 16);		-- width

    port (
	clk	 : in  std_logic;			     -- main clock
	rst_n	 : in  std_logic;			     -- active low reset
	seed	 : in  std_logic_vector(WIDTH-1 downto 0);   -- seed
	poly	 : in  std_logic_vector(WIDTH-1 downto 0);   -- polynomial, x"D008" for x16+x15+x13+1
	lfsr_out : out std_logic_vector(WIDTH-1 downto 0));  -- lfsr output

end entity lfsr_generic;

architecture rtl of lfsr_generic is

    -- -2008 use unitary AND without parameter instead of call:
    function reduce_xor (inp : std_logic_vector) return std_logic is
	variable retval	     : std_logic := '0';
    begin
	for i in inp'range loop
	    retval			 := retval xor inp(i);
	end loop;
	return retval;
    end function;

    signal lfsr_poly	: std_logic_vector(WIDTH-1 downto 0);
    signal lfsr_out_buf : std_logic_vector(WIDTH-1 downto 0);
    signal feedback	: std_logic;

begin  -- architecture rtl

    feedback  <= reduce_xor(lfsr_poly);
    lfsr_poly <= poly and lfsr_out_buf;
    lfsr_out  <= lfsr_out_buf;

    PROC_LFSR : process (clk, rst_n) is
    begin  -- process PROC_LFSR
	if rst_n = '0' then		-- asynchronous reset (active low)
	    lfsr_out_buf <= seed;
	elsif rising_edge(clk) then	-- rising clock edge
	    lfsr_out_buf <= lfsr_out_buf(WIDTH-2 downto 0) & feedback;
	end if;
    end process PROC_LFSR;

end architecture rtl;

ecc/ecc_dec_8.vhd
-------------------------------------------------------------------------------
-- Title      : ECC Decoder
-- Project    : 
-------------------------------------------------------------------------------
-- File	      : ecc_dec_8.vhd
-- Author     : Efe  <efe@efeASUS>
-- Company    : 
-- Created    : 2022-10-12
-- Last update: 2022-10-13
-- Platform   : 
-- Standard   : VHDL'93/02
-------------------------------------------------------------------------------
-- Description: 
-------------------------------------------------------------------------------
-- Copyright (c) 2022 
-------------------------------------------------------------------------------
-- Revisions  :
-- Date	       Version	Author	Description
-- 2022-10-12  1.0	efe	Created
-------------------------------------------------------------------------------

library ieee;
use ieee.std_logic_1164.all;

entity ecc_dec_8 is

    port (
	clk   : in  std_logic;			    -- main clock
	rst_n : in  std_logic;			    -- active low reset
	din   : in  std_logic_vector(12 downto 0);  -- input
	dout  : out std_logic_vector(7 downto 0);   -- output
	serr  : out std_logic;			    -- single bit error
	derr  : out std_logic);			    -- double bit error

end entity ecc_dec_8;

architecture rtl of ecc_dec_8 is

    signal term1 : std_logic;
    signal term2 : std_logic;
    signal term3 : std_logic;
    signal term4 : std_logic;
    signal term5 : std_logic;

begin  -- architecture rtl

    term1 <= din(12) xor din(11) xor din(10) xor din(9) xor din(8) xor din(7) xor din(6) xor din(5) xor din(4) xor din(3) xor din(2) xor din(1) xor din(0);
    term2 <= din(12) xor din(10) xor din(8) xor din(6) xor din(4) xor din(2);
    term3 <= din(11) xor din(10) xor din(7) xor din(6) xor din(3) xor din(2);
    term4 <= din(9) xor din(8) xor din(7) xor din(6) xor din(1);
    term5 <= din(5) xor din(4) xor din(3) xor din(2) xor din(1);

    PROC_DEC : process (clk, rst_n) is
    begin  -- process PROC_DEC
	if rst_n = '0' then		-- asynchronous reset (active low)
	    dout <= (others => '0');
	    serr <= '0';
	    derr <= '0';
	elsif rising_edge(clk) then	-- rising clock edge

	    dout(7) <= (din(10) and not(term1 and ((term2 and term3) and (not(term4) and not(term5))))) or
		       (not din(10) and (term1 and ((term2 and term3) and (not(term4) and not(term5)))));


	    dout(6) <= (din(8) and not(term1 and ((term2 and not(term3)) and (term4 and not(term5))))) or
		       (not din(8) and (term1 and ((term2 and not(term3)) and (term4 and not(term5)))));

	    dout(5) <= (din(7) and not(term1 and ((not(term2) and term3) and (term4 and not(term5))))) or
		       (not din(7) and (term1 and ((not(term2) and term3) and (term4 and not(term5)))));

	    dout(4) <= (din(6) and not(term1 and ((term2 and term3) and (term4 and not(term5))))) or
		       (not din(6) and (term1 and ((term2 and term3) and (term4 and not(term5)))));

	    dout(3) <= (din(4) and not(term1 and ((term2 and not(term3)) and (not(term4) and term5)))) or
		       (not din(4) and (term1 and ((term2 and not(term3)) and (not(term4) and term5))));

	    dout(2) <= (din(3) and (not(term1 and ((not(term2) and term3) and (not(term4) and term5))))) or
		       (not din(3) and (term1 and ((not(term2) and term3) and (not(term4) and term5))));

	    dout(1) <= (din(2) and (not(term1 and ((term2 and term3) and (not(term4) and term5))))) or
		       (not din(2) and (term1 and ((term2 and term3) and (not(term4) and term5))));

	    dout(0) <= (din(1) and (not(term1 and ((not(term2) and not(term3)) and (term4 and term5))))) or
		       (not din(1) and (term1 and ((not(term2) and not(term3)) and (term4 and term5))));

	    derr <= (not term1) and (term2 or term3 or term4 or term5);

	    serr <= term1;

	end if;
    end process PROC_DEC;

end architecture rtl;

ecc/ecc_enc_8.vhd
-------------------------------------------------------------------------------
-- Title      : ECC Encoder
-- Project    : 
-------------------------------------------------------------------------------
-- File	      : ecc_enc_8.vhd
-- Author     : Efe  <efe@efeASUS>
-- Company    : 
-- Created    : 2022-10-12
-- Last update: 2022-10-12
-- Platform   : 
-- Standard   : VHDL'93/02
-------------------------------------------------------------------------------
-- Description: 
-------------------------------------------------------------------------------
-- Copyright (c) 2022 
-------------------------------------------------------------------------------
-- Revisions  :
-- Date	       Version	Author	Description
-- 2022-10-12  1.0	efe	Created
-------------------------------------------------------------------------------

library ieee;
use ieee.std_logic_1164.all;

entity ecc_enc_8 is

    port (
	clk   : in  std_logic;			     -- main clock
	rst_n : in  std_logic;			     -- active low reset
	din   : in  std_logic_vector(7 downto 0);    -- input
	dout  : out std_logic_vector(12 downto 0));  -- output

end entity ecc_enc_8;

architecture rtl of ecc_enc_8 is

begin  -- architecture rtl

    PROC_ENC : process (clk, rst_n) is
    begin  -- process PROC_ENC
	if rst_n = '0' then		-- asynchronous reset (active low)
	    dout	     <= (others => '0');
	elsif rising_edge(clk) then	-- rising clock edge
	    dout(12)	     <= din(7) xor din(6) xor din(4) xor din(3) xor din(1);
	    dout(11)	     <= din(7) xor din(5) xor din(4) xor din(2) xor din(1);
	    dout(10)	     <= din(7);
	    dout(9)	     <= din(6) xor din(5) xor din(4) xor din(0);
	    dout(8 downto 6) <= din(6 downto 4);
	    dout(5)	     <= din(3) xor din(2) xor din(1) xor din(0);
	    dout(4 downto 1) <= din(3 downto 0);
	    dout(0)	     <= din(7) xor din(6) xor din(5) xor din(3) xor din(2) xor din(0);
	end if;
    end process PROC_ENC;

end architecture rtl;

ecc/top.vhd
library ieee;
use ieee.std_logic_1164.all;

entity top is

    port (
	clk   : in  std_logic;			   -- main clock
	rst_n : in  std_logic;			   -- active low reset
	dout  : out std_logic_vector(7 downto 0);  -- output
	serr  : out std_logic;			   -- single error
	derr  : out std_logic);			   -- double error

end entity top;

architecture rtl of top is

    component ecc_enc_8 is
	port (
	    clk	  : in	std_logic;
	    rst_n : in	std_logic;
	    din	  : in	std_logic_vector(7 downto 0);
	    dout  : out std_logic_vector(12 downto 0));
    end component ecc_enc_8;

    component ecc_dec_8 is
	port (
	    clk	  : in	std_logic;
	    rst_n : in	std_logic;
	    din	  : in	std_logic_vector(12 downto 0);
	    dout  : out std_logic_vector(7 downto 0);
	    serr  : out std_logic;
	    derr  : out std_logic);
    end component ecc_dec_8;

    component lfsr_generic is
	generic (
	    WIDTH    :	   integer);
	port (
	    clk	     : in  std_logic;
	    rst_n    : in  std_logic;
	    seed     : in  std_logic_vector(WIDTH-1 downto 0);
	    poly     : in  std_logic_vector(WIDTH-1 downto 0);
	    lfsr_out : out std_logic_vector(WIDTH-1 downto 0));
    end component lfsr_generic;

    signal enc_out  : std_logic_vector(12 downto 0);
    signal lfsr_out : std_logic_vector(7 downto 0);
    constant seed   : std_logic_vector(7 downto 0) := x"EF";
    constant poly   : std_logic_vector(7 downto 0) := x"D3";

begin  -- architecture rtl

    U_ENC : entity work.ecc_enc_8
	port map (
	    clk	  => clk,
	    rst_n => rst_n,
	    din	  => lfsr_out,
	    dout  => enc_out);

    U_DEC : entity work.ecc_dec_8
	port map (
	    clk	  => clk,
	    rst_n => rst_n,
	    din	  => enc_out,
	    dout  => dout,
	    serr  => serr,
	    derr  => derr);

    U_LFSR : entity work.lfsr_generic
	generic map (
	    WIDTH    => 8)
	port map (
	    clk	     => clk,
	    rst_n    => rst_n,
	    seed     => seed,
	    poly     => poly,
	    lfsr_out => lfsr_out);

end architecture rtl;

ecc/top_tb.vhd
-------------------------------------------------------------------------------
-- Title      : Testbench for design "top"
-- Project    : 
-------------------------------------------------------------------------------
-- File	      : top_tb.vhd
-- Author     : Efe  <efe@efeASUS>
-- Company    : 
-- Created    : 2022-10-12
-- Last update: 2022-10-12
-- Platform   : 
-- Standard   : VHDL'93/02
-------------------------------------------------------------------------------
-- Description: 
-------------------------------------------------------------------------------
-- Copyright (c) 2022 
-------------------------------------------------------------------------------
-- Revisions  :
-- Date	       Version	Author	Description
-- 2022-10-12  1.0	efe	Created
-------------------------------------------------------------------------------

library ieee;
use ieee.std_logic_1164.all;

--------------------------------------------------------------------------------------------------------------------------------------------------------------------------------------------------------

entity top_tb is

end entity top_tb;

--------------------------------------------------------------------------------------------------------------------------------------------------------------------------------------------------------

architecture tb of top_tb is

    -- component ports
    signal clk	 : std_logic := '0';
    signal rst_n : std_logic := '0';
    signal dout	 : std_logic_vector(7 downto 0);
    signal serr	 : std_logic;
    signal derr	 : std_logic;

    procedure waitNre(signal clock : std_logic; n : positive) is
    begin
	for i in 1 to n loop
	    wait until rising_edge(clk);
	end loop;  -- i in l to n loop
    end procedure waitNre;

begin  -- architecture tb

    -- component instantiation
    U_DUT : entity work.top
	port map (
	    clk	  => clk,
	    rst_n => rst_n,
	    dout  => dout,
	    serr  => serr,
	    derr  => derr);

    -- clock generation
    clk <= not clk after 10 ns;

    -- waveform generation
    PROC_STIMULI : process
    begin
	-- insert signal assignments here
	waitNre(clk, 5);
	rst_n <= '1';
	waitNre(clk, 5);
	wait until dout = x"EF";
	assert false report "SEED FOUND";
	waitNre(clk, 5);
	assert false report "SIM DONE" severity failure;
    end process PROC_STIMULI;



end architecture tb;

ecc/ecc.vcd
$date
  Thu Oct 13 00:21:46 2022
$end
$version
  GHDL v0
$end
$timescale
  1 fs
$end
$scope module standard $end
$upscope $end
$scope module std_logic_1164 $end
$upscope $end
$scope module numeric_std $end
$upscope $end
$scope module top_tb $end
$var reg 1 ! clk $end
$var reg 1 " rst_n $end
$var reg 8 # dout[7:0] $end
$var reg 1 $ serr $end
$var reg 1 % derr $end
$scope module u_dut $end
$var reg 1 & clk $end
$var reg 1 ' rst_n $end
$var reg 8 ( dout[7:0] $end
$var reg 1 ) serr $end
$var reg 1 * derr $end
$var reg 13 + enc_out[12:0] $end
$var reg 8 , lfsr_out[7:0] $end
$scope module u_enc $end
$var reg 1 - clk $end
$var reg 1 . rst_n $end
$var reg 8 / din[7:0] $end
$var reg 13 0 dout[12:0] $end
$upscope $end
$scope module u_dec $end
$var reg 1 1 clk $end
$var reg 1 2 rst_n $end
$var reg 13 3 din[12:0] $end
$var reg 8 4 dout[7:0] $end
$var reg 1 5 serr $end
$var reg 1 6 derr $end
$var reg 1 7 term1 $end
$var reg 1 8 term2 $end
$var reg 1 9 term3 $end
$var reg 1 : term4 $end
$var reg 1 ; term5 $end
$upscope $end
$scope module u_lfsr $end
$var reg 1 < clk $end
$var reg 1 = rst_n $end
$var reg 8 > seed[7:0] $end
$var reg 8 ? poly[7:0] $end
$var reg 8 @ lfsr_out[7:0] $end
$var reg 8 A lfsr_poly[7:0] $end
$var reg 8 B lfsr_out_buf[7:0] $end
$var reg 1 C feedback $end
$upscope $end
$upscope $end
$upscope $end
$enddefinitions $end
#0
0!
0"
b00000000 #
0$
0%
0&
0'
b00000000 (
0)
0*
b0000000000000 +
b11101111 ,
0-
0.
b11101111 /
b0000000000000 0
01
02
b0000000000000 3
b00000000 4
05
06
07
08
09
0:
0;
0<
0=
b11101111 >
b11010011 ?
b11101111 @
b11000011 A
b11101111 B
0C
#10000000
1!
1&
1-
11
1<
#20000000
0!
0&
0-
01
0<
#30000000
1!
1&
1-
11
1<
#40000000
0!
0&
0-
01
0<
#50000000
1!
1&
1-
11
1<
#60000000
0!
0&
0-
01
0<
#70000000
1!
1&
1-
11
1<
#80000000
0!
0&
0-
01
0<
#90000000
1!
1"
1&
1'
1-
1.
11
12
1<
1=
#100000000
0!
0&
0-
01
0<
#110000000
1!
1&
b0011110011110 +
b11011110 ,
1-
b11011110 /
b0011110011110 0
11
b0011110011110 3
1<
b11011110 @
b11010010 A
b11011110 B
#120000000
0!
0&
0-
01
0<
#130000000
1!
b11101111 #
1&
b11101111 (
b1010101111100 +
b10111100 ,
1-
b10111100 /
b1010101111100 0
11
b1010101111100 3
b11101111 4
1<
b10111100 @
b10010000 A
b10111100 B
#140000000
0!
0&
0-
01
0<
#150000000
1!
b11011110 #
1&
b11011110 (
b1010011011000 +
b01111000 ,
1-
b01111000 /
b1010011011000 0
11
b1010011011000 3
b11011110 4
1<
b01111000 @
b01010000 A
b01111000 B
#160000000
0!
0&
0-
01
0<
#170000000
1!
b10111100 #
1&
b10111100 (
b1001111110001 +
b11110000 ,
1-
b11110000 /
b1001111110001 0
11
b1001111110001 3
b10111100 4
1<
b11110000 @
b11010000 A
b11110000 B
1C
#180000000
0!
0&
0-
01
0<
#190000000
1!
b01111000 #
1&
b01111000 (
b1111111000001 +
b11100001 ,
1-
b11100001 /
b1111111000001 0
11
b1111111000001 3
b01111000 4
1<
b11100001 @
b11000001 A
b11100001 B
#200000000
0!
0&
0-
01
0<
#210000000
1!
b11110000 #
1&
b11110000 (
b0011110100010 +
b11000011 ,
1-
b11000011 /
b0011110100010 0
11
b0011110100010 3
b11110000 4
1<
b11000011 @
b11000011 A
b11000011 B
0C
#220000000
0!
0&
0-
01
0<
#230000000
1!
b11100001 #
1&
b11100001 (
b1010100000111 +
b10000110 ,
1-
b10000110 /
b1010100000111 0
11
b1010100000111 3
b11100001 4
1<
b10000110 @
b10000010 A
b10000110 B
#240000000
0!
0&
0-
01
0<
#250000000
1!
b11000011 #
1&
b11000011 (
b0110000001100 +
b00001100 ,
1-
b00001100 /
b0110000001100 0
11
b0110000001100 3
b11000011 4
1<
b00001100 @
b00000000 A
b00001100 B
#260000000
0!
0&
0-
01
0<
#270000000
1!
b10000110 #
1&
b10000110 (
b1100000011000 +
b00011000 ,
1-
b00011000 /
b1100000011000 0
11
b1100000011000 3
b10000110 4
1<
b00011000 @
b00010000 A
b00011000 B
1C
#280000000
0!
0&
0-
01
0<
#290000000
1!
b00001100 #
1&
b00001100 (
b0101001110001 +
b00110001 ,
1-
b00110001 /
b0101001110001 0
11
b0101001110001 3
b00001100 4
1<
b00110001 @
b00010001 A
b00110001 B
0C
#300000000
0!
0&
0-
01
0<
#310000000
1!
b00011000 #
1&
b00011000 (
b1001011100010 +
b01100010 ,
1-
b01100010 /
b1001011100010 0
11
b1001011100010 3
b00011000 4
1<
b01100010 @
b01000010 A
b01100010 B
#320000000
0!
0&
0-
01
0<
#330000000
1!
b00110001 #
1&
b00110001 (
b0000110100100 +
b11000100 ,
1-
b11000100 /
b0000110100100 0
11
b0000110100100 3
b00110001 4
1<
b11000100 @
b11000000 A
b11000100 B
#340000000
0!
0&
0-
01
0<
#350000000
1!
b01100010 #
1&
b01100010 (
b0011100101001 +
b10001000 ,
1-
b10001000 /
b0011100101001 0
11
b0011100101001 3
b01100010 4
1<
b10001000 @
b10000000 A
b10001000 B
1C
#360000000
0!
0&
0-
01
0<
#370000000
1!
b11000100 #
1&
b11000100 (
b0110000110000 +
b00010001 ,
1-
b00010001 /
b0110000110000 0
11
b0110000110000 3
b11000100 4
1<
b00010001 @
b00010001 A
b00010001 B
0C
#380000000
0!
0&
0-
01
0<
#390000000
1!
b10001000 #
1&
b10001000 (
b1100001100011 +
b00100010 ,
1-
b00100010 /
b1100001100011 0
11
b1100001100011 3
b10001000 4
1<
b00100010 @
b00000010 A
b00100010 B
1C
#400000000
0!
0&
0-
01
0<
#410000000
1!
b00010001 #
1&
b00010001 (
b1001010100101 +
b01000101 ,
1-
b01000101 /
b1001010100101 0
11
b1001010100101 3
b00010001 4
1<
b01000101 @
b01000001 A
b01000101 B
0C
#420000000
0!
0&
0-
01
0<
#430000000
1!
b00100010 #
1&
b00100010 (
b1100100001011 +
b10001010 ,
1-
b10001010 /
b1100100001011 0
11
b1100100001011 3
b00100010 4
1<
b10001010 @
b10000010 A
b10001010 B
#440000000
0!
0&
0-
01
0<
#450000000
1!
b01000101 #
1&
b01000101 (
b1010000010100 +
b00010100 ,
1-
b00010100 /
b1010000010100 0
11
b1010000010100 3
b01000101 4
1<
b00010100 @
b00010000 A
b00010100 B
1C
#460000000
0!
0&
0-
01
0<
#470000000
1!
b10001010 #
1&
b10001010 (
b1001001101001 +
b00101001 ,
1-
b00101001 /
b1001001101001 0
11
b1001001101001 3
b10001010 4
1<
b00101001 @
b00000001 A
b00101001 B
#480000000
0!
0&
0-
01
0<
#490000000
1!
b00010100 #
1&
b00010100 (
b1100010010011 +
b01010011 ,
1-
b01010011 /
b1100010010011 0
11
b1100010010011 3
b00010100 4
1<
b01010011 @
b01010011 A
b01010011 B
0C
#500000000
0!
0&
0-
01
0<
#510000000
1!
b00101001 #
1&
b00101001 (
b1001101000110 +
b10100110 ,
1-
b10100110 /
b1001101000110 0
11
b1001101000110 3
b00101001 4
1<
b10100110 @
b10000010 A
b10100110 B
#520000000
0!
0&
0-
01
0<
#530000000
1!
b01010011 #
1&
b01010011 (
b0011010001101 +
b01001100 ,
1-
b01001100 /
b0011010001101 0
11
b0011010001101 3
b01010011 4
1<
b01001100 @
b01000000 A
b01001100 B
1C
#540000000
0!
0&
0-
01
0<
#550000000
1!
b10100110 #
1&
b10100110 (
b0101100011001 +
b10011001 ,
1-
b10011001 /
b0101100011001 0
11
b0101100011001 3
b10100110 4
1<
b10011001 @
b10010001 A
b10011001 B
#560000000
0!
0&
0-
01
0<
#570000000
1!
b01001100 #
1&
b01001100 (
b1010001010011 +
b00110011 ,
1-
b00110011 /
b1010001010011 0
11
b1010001010011 3
b01001100 4
1<
b00110011 @
b00010011 A
b00110011 B
#580000000
0!
0&
0-
01
0<
#590000000
1!
b10011001 #
1&
b10011001 (
b0101011000110 +
b01100111 ,
1-
b01100111 /
b0101011000110 0
11
b0101011000110 3
b10011001 4
1<
b01100111 @
b01000011 A
b01100111 B
#600000000
0!
0&
0-
01
0<
#610000000
1!
b00110011 #
1&
b00110011 (
b0101110101110 +
b11001111 ,
1-
b11001111 /
b0101110101110 0
11
b0101110101110 3
b00110011 4
1<
b11001111 @
b11000011 A
b11001111 B
0C
#620000000
0!
0&
0-
01
0<
#630000000
1!
b01100111 #
1&
b01100111 (
b0110100011111 +
b10011110 ,
1-
b10011110 /
b0110100011111 0
11
b0110100011111 3
b01100111 4
1<
b10011110 @
b10010010 A
b10011110 B
1C
#640000000
0!
0&
0-
01
0<
#650000000
1!
b11001111 #
1&
b11001111 (
b0011001111101 +
b00111101 ,
1-
b00111101 /
b0011001111101 0
11
b0011001111101 3
b11001111 4
1<
b00111101 @
b00010001 A
b00111101 B
0C
#660000000
0!
0&
0-
01
0<
#670000000
1!
b10011110 #
1&
b10011110 (
b0101011111010 +
b01111010 ,
1-
b01111010 /
b0101011111010 0
11
b0101011111010 3
b10011110 4
1<
b01111010 @
b01010010 A
b01111010 B
1C
#680000000
0!
0&
0-
01
0<
#690000000
1!
b00111101 #
1&
b00111101 (
b0101111010101 +
b11110101 ,
1-
b11110101 /
b0101111010101 0
11
b0101111010101 3
b00111101 4
1<
b11110101 @
b11010001 A
b11110101 B
0C
#700000000
0!
0&
0-
01
0<
#710000000
1!
b01111010 #
1&
b01111010 (
b1010111001011 +
b11101010 ,
1-
b11101010 /
b1010111001011 0
11
b1010111001011 3
b01111010 4
1<
b11101010 @
b11000010 A
b11101010 B
1C
#720000000
0!
0&
0-
01
0<
#730000000
1!
b11110101 #
1&
b11110101 (
b0110110010100 +
b11010101 ,
1-
b11010101 /
b0110110010100 0
11
b0110110010100 3
b11110101 4
1<
b11010101 @
b11010001 A
b11010101 B
0C
#740000000
0!
0&
0-
01
0<
#750000000
1!
b11101010 #
1&
b11101010 (
b1111101001010 +
b10101010 ,
1-
b10101010 /
b1111101001010 0
11
b1111101001010 3
b11101010 4
1<
b10101010 @
b10000010 A
b10101010 B
#760000000
0!
0&
0-
01
0<
#770000000
1!
b11010101 #
1&
b11010101 (
b1111010010101 +
b01010100 ,
1-
b01010100 /
b1111010010101 0
11
b1111010010101 3
b11010101 4
1<
b01010100 @
b01010000 A
b01010100 B
#780000000
0!
0&
0-
01
0<
#790000000
1!
b10101010 #
1&
b10101010 (
b0000101101000 +
b10101000 ,
1-
b10101000 /
b0000101101000 0
11
b0000101101000 3
b10101010 4
1<
b10101000 @
b10000000 A
b10101000 B
1C
#800000000
0!
0&
0-
01
0<
#810000000
1!
b01010100 #
1&
b01010100 (
b0011010110001 +
b01010001 ,
1-
b01010001 /
b0011010110001 0
11
b0011010110001 3
b01010100 4
1<
b01010001 @
b01010001 A
b01010001 B
#820000000
0!
0&
0-
01
0<
#830000000
1!
b10101000 #
1&
b10101000 (
b0101101100010 +
b10100011 ,
1-
b10100011 /
b0101101100010 0
11
b0101101100010 3
b10101000 4
1<
b10100011 @
b10000011 A
b10100011 B
#840000000
0!
0&
0-
01
0<
#850000000
1!
b01010001 #
1&
b01010001 (
b0110010000111 +
b01000111 ,
1-
b01000111 /
b0110010000111 0
11
b0110010000111 3
b01010001 4
1<
b01000111 @
b01000011 A
b01000111 B
#860000000
0!
0&
0-
01
0<
#870000000
1!
b10100011 #
1&
b10100011 (
b0000100101111 +
b10001111 ,
1-
b10001111 /
b0000100101111 0
11
b0000100101111 3
b10100011 4
1<
b10001111 @
b10000011 A
b10001111 B
#880000000
0!
0&
0-
01
0<
#890000000
1!
b01000111 #
1&
b01000111 (
b1111000011110 +
b00011111 ,
1-
b00011111 /
b1111000011110 0
11
b1111000011110 3
b01000111 4
1<
b00011111 @
b00010011 A
b00011111 B
#900000000
0!
0&
0-
01
0<
#910000000
1!
b10001111 #
1&
b10001111 (
b1100001011111 +
b00111111 ,
1-
b00111111 /
b1100001011111 0
11
b1100001011111 3
b10001111 4
1<
b00111111 @
b00111111 B
#920000000
0!
0&
0-
01
0<
#930000000
1!
b00011111 #
1&
b00011111 (
b1001011011110 +
b01111111 ,
1-
b01111111 /
b1001011011110 0
11
b1001011011110 3
b00011111 4
1<
b01111111 @
b01010011 A
b01111111 B
0C
#940000000
0!
0&
0-
01
0<
#950000000
1!
b00111111 #
1&
b00111111 (
b0000111011111 +
b11111110 ,
1-
b11111110 /
b0000111011111 0
11
b0000111011111 3
b00111111 4
1<
b11111110 @
b11010010 A
b11111110 B
#960000000
0!
0&
0-
01
0<
#970000000
1!
b01111111 #
1&
b01111111 (
b1111111111101 +
b11111100 ,
1-
b11111100 /
b1111111111101 0
11
b1111111111101 3
b01111111 4
1<
b11111100 @
b11010000 A
b11111100 B
1C
#980000000
0!
0&
0-
01
0<
#990000000
1!
b11111110 #
1&
b11111110 (
b0011111011001 +
b11111001 ,
1-
b11111001 /
b0011111011001 0
11
b0011111011001 3
b11111110 4
1<
b11111001 @
b11010001 A
b11111001 B
0C
#1000000000
0!
0&
0-
01
0<
#1010000000
1!
b11111100 #
1&
b11111100 (
b0110111010011 +
b11110010 ,
1-
b11110010 /
b0110111010011 0
11
b0110111010011 3
b11111100 4
1<
b11110010 @
b11010010 A
b11110010 B
#1020000000
0!
0&
0-
01
0<
#1030000000
1!
b11111001 #
1&
b11111001 (
b0011111100101 +
b11100100 ,
1-
b11100100 /
b0011111100101 0
11
b0011111100101 3
b11111001 4
1<
b11100100 @
b11000000 A
b11100100 B
#1040000000
0!
0&
0-
01
0<
#1050000000
1!
b11110010 #
1&
b11110010 (
b0110110101000 +
b11001000 ,
1-
b11001000 /
b0110110101000 0
11
b0110110101000 3
b11110010 4
1<
b11001000 @
b11001000 B
#1060000000
0!
0&
0-
01
0<
#1070000000
1!
b11100100 #
1&
b11100100 (
b1111100110001 +
b10010000 ,
1-
b10010000 /
b1111100110001 0
11
b1111100110001 3
b11100100 4
1<
b10010000 @
b10010000 A
b10010000 B
#1080000000
0!
0&
0-
01
0<
#1090000000
1!
b11001000 #
1&
b11001000 (
b0011001000001 +
b00100000 ,
1-
b00100000 /
b0011001000001 0
11
b0011001000001 3
b11001000 4
1<
b00100000 @
b00000000 A
b00100000 B
#1100000000
0!
0&
0-
01
0<
#1110000000
1!
b10010000 #
1&
b10010000 (
b0101010000001 +
b01000000 ,
1-
b01000000 /
b0101010000001 0
11
b0101010000001 3
b10010000 4
1<
b01000000 @
b01000000 A
b01000000 B
1C
#1120000000
0!
0&
0-
01
0<
#1130000000
1!
b00100000 #
1&
b00100000 (
b1001100000001 +
b10000001 ,
1-
b10000001 /
b1001100000001 0
11
b1001100000001 3
b00100000 4
1<
b10000001 @
b10000001 A
b10000001 B
0C
#1140000000
0!
0&
0-
01
0<
#1150000000
1!
b01000000 #
1&
b01000000 (
b1111000100010 +
b00000010 ,
1-
b00000010 /
b1111000100010 0
11
b1111000100010 3
b01000000 4
1<
b00000010 @
b00000010 A
b00000010 B
1C
#1160000000
0!
0&
0-
01
0<
#1170000000
1!
b10000001 #
1&
b10000001 (
b1100000100100 +
b00000101 ,
1-
b00000101 /
b1100000100100 0
11
b1100000100100 3
b10000001 4
1<
b00000101 @
b00000001 A
b00000101 B
#1180000000
0!
0&
0-
01
0<
#1190000000
1!
b00000010 #
1&
b00000010 (
b0101000001010 +
b00001011 ,
1-
b00001011 /
b0101000001010 0
11
b0101000001010 3
b00000010 4
1<
b00001011 @
b00000011 A
b00001011 B
0C
#1200000000
0!
0&
0-
01
0<
#1210000000
1!
b00000101 #
1&
b00000101 (
b0101000110110 +
b00010110 ,
1-
b00010110 /
b0101000110110 0
11
b0101000110110 3
b00000101 4
1<
b00010110 @
b00010010 A
b00010110 B
#1220000000
0!
0&
0-
01
0<
#1230000000
1!
b00001011 #
1&
b00001011 (
b0101001001101 +
b00101100 ,
1-
b00101100 /
b0101001001101 0
11
b0101001001101 3
b00001011 4
1<
b00101100 @
b00000000 A
b00101100 B
#1240000000
0!
0&
0-
01
0<
#1250000000
1!
b00010110 #
1&
b00010110 (
b1001010011001 +
b01011000 ,
1-
b01011000 /
b1001010011001 0
11
b1001010011001 3
b00010110 4
1<
b01011000 @
b01010000 A
b01011000 B
#1260000000
0!
0&
0-
01
0<
#1270000000
1!
b00101100 #
1&
b00101100 (
b1100101110000 +
b10110000 ,
1-
b10110000 /
b1100101110000 0
11
b1100101110000 3
b00101100 4
1<
b10110000 @
b10010000 A
b10110000 B
#1280000000
0!
0&
0-
01
0<
#1290000000
1!
b01011000 #
1&
b01011000 (
b0110011000000 +
b01100000 ,
1-
b01100000 /
b0110011000000 0
11
b0110011000000 3
b01011000 4
1<
b01100000 @
b01000000 A
b01100000 B
1C
#1300000000
0!
0&
0-
01
0<
#1310000000
1!
b10110000 #
1&
b10110000 (
b1100110000000 +
b11000001 ,
1-
b11000001 /
b1100110000000 0
11
b1100110000000 3
b10110000 4
1<
b11000001 @
b11000001 A
b11000001 B
#1320000000
0!
0&
0-
01
0<
#1330000000
1!
b01100000 #
1&
b01100000 (
b0110100100011 +
b10000011 ,
1-
b10000011 /
b0110100100011 0
11
b0110100100011 3
b01100000 4
1<
b10000011 @
b10000011 A
b10000011 B
#1340000000
0!
0&
0-
01
0<
#1350000000
1!
b11000001 #
1&
b11000001 (
b0011000000110 +
b00000111 ,
1-
b00000111 /
b0011000000110 0
11
b0011000000110 3
b11000001 4
1<
b00000111 @
b00000011 A
b00000111 B
0C
#1360000000
0!
0&
0-
01
0<
#1370000000
1!
b10000011 #
1&
b10000011 (
b1001000101110 +
b00001110 ,
1-
b00001110 /
b1001000101110 0
11
b1001000101110 3
b10000011 4
1<
b00001110 @
b00000010 A
b00001110 B
1C
#1380000000
0!
0&
0-
01
0<
#1390000000
1!
b00000111 #
1&
b00000111 (
b0000000111100 +
b00011101 ,
1-
b00011101 /
b0000000111100 0
11
b0000000111100 3
b00000111 4
1<
b00011101 @
b00010001 A
b00011101 B
0C
#1400000000
0!
0&
0-
01
0<
#1410000000
1!
b00001110 #
1&
b00001110 (
b0000001111011 +
b00111010 ,
1-
b00111010 /
b0000001111011 0
11
b0000001111011 3
b00001110 4
1<
b00111010 @
b00010010 A
b00111010 B
#1420000000
0!
0&
0-
01
0<
#1430000000
1!
b00011101 #
1&
b00011101 (
b1100011010100 +
b01110100 ,
1-
b01110100 /
b1100011010100 0
11
b1100011010100 3
b00011101 4
1<
b01110100 @
b01010000 A
b01110100 B
#1440000000
0!
0&
0-
01
0<
#1450000000
1!
b00111010 #
1&
b00111010 (
b0101111101001 +
b11101000 ,
1-
b11101000 /
b0101111101001 0
11
b0101111101001 3
b00111010 4
1<
b11101000 @
b11000000 A
b11101000 B
#1460000000
0!
0&
0-
01
0<
